mcli/__init__.py
mcli/main.py
mrMonosCli-0.1.4.dist-info/LICENSE.txt
mrMonosCli-0.1.4.dist-info/METADATA
mrMonosCli-0.1.4.dist-info/WHEEL
mrMonosCli-0.1.4.dist-info/top_level.txt
mrMonosCli-0.1.4.dist-info/RECORD
