Metadata-Version: 2.1
Name: mrMonosCli
Version: 0.1.4
Summary: New support module for CLI
Author-email: mrMonos <panekmichas@gmail.com>
Project-URL: Homepage, https://github.com/mrMonos/mrMonosCli
Project-URL: Bug Tracker, https://github.com/mrMonos/mrMonosCli/issues
Classifier: Programming Language :: Python :: 3
Classifier: License :: OSI Approved :: Mozilla Public License 2.0 (MPL 2.0)
Classifier: Operating System :: OS Independent
Classifier: Natural Language :: English
Requires-Python: >=3.7
License-File: LICENSE.txt
Requires-Dist: colorama
